al_struct/algorithms/__init__.py
al_struct/algorithms/search/__init__.py
al_struct/algorithms/search/binary_search.py
al_struct/algorithms/search/linear_search.py
al_struct/algorithms/sort/__init__.py
al_struct/algorithms/sort/bubble.py
al_struct/algorithms/sort/insertion.py
al_struct/algorithms/sort/merge.py
al_struct/algorithms/sort/quick.py
al_struct/algorithms/sort/selection.py
al_struct/data_structures/__init__.py
al_struct/data_structures/pair.py
al_struct/data_structures/lists/__init__.py
al_struct/data_structures/lists/base_linked_list.py
al_struct/data_structures/lists/doubly_linked_list.py
al_struct/data_structures/lists/singly_linked_list.py
al_struct/data_structures/lists/sorted_linked_list.py
al_struct/data_structures/queues/__init__.py
al_struct/data_structures/queues/queue.py
al_struct/data_structures/stacks/__init__.py
al_struct/data_structures/stacks/stack.py
al_struct/data_structures/trees/__init__.py
al_struct/data_structures/trees/bst.py
al_struct/utils/__init__.py
al_struct/utils/exceptions.py
al_struct/utils/nodes.py
PyAlStruct-0.14.0.dist-info/LICENSE
PyAlStruct-0.14.0.dist-info/METADATA
PyAlStruct-0.14.0.dist-info/WHEEL
PyAlStruct-0.14.0.dist-info/top_level.txt
PyAlStruct-0.14.0.dist-info/RECORD
